zoegas/__init__.py
zoegas/constants.py
zoegas/dictionary.xml
zoegas/dictionary.yaml
zoegas/reader.py
zoegas/tests.py
zoegas/utils.py
zoegas/__pycache__/__init__.cpython-37.pyc
zoegas/__pycache__/__init__.cpython-38.pyc
zoegas/__pycache__/constants.cpython-37.pyc
zoegas/entries_before_change_name_mark/a.dsl
zoegas/entries_before_change_name_mark/aa.dsl
zoegas/entries_before_change_name_mark/ae.dsl
zoegas/entries_before_change_name_mark/b.dsl
zoegas/entries_before_change_name_mark/d.dsl
zoegas/entries_before_change_name_mark/e.dsl
zoegas/entries_before_change_name_mark/f.dsl
zoegas/entries_before_change_name_mark/g.dsl
zoegas/entries_before_change_name_mark/h.dsl
zoegas/entries_before_change_name_mark/i.dsl
zoegas/entries_before_change_name_mark/ii.dsl
zoegas/entries_before_change_name_mark/j.dsl
zoegas/entries_before_change_name_mark/k.dsl
zoegas/entries_before_change_name_mark/l.dsl
zoegas/entries_before_change_name_mark/m.dsl
zoegas/entries_before_change_name_mark/n.dsl
zoegas/entries_before_change_name_mark/o.dsl
zoegas/entries_before_change_name_mark/oe.dsl
zoegas/entries_before_change_name_mark/oo.dsl
zoegas/entries_before_change_name_mark/oum.dsl
zoegas/entries_before_change_name_mark/p.dsl
zoegas/entries_before_change_name_mark/r.dsl
zoegas/entries_before_change_name_mark/s.dsl
zoegas/entries_before_change_name_mark/t.dsl
zoegas/entries_before_change_name_mark/th.dsl
zoegas/entries_before_change_name_mark/u.dsl
zoegas/entries_before_change_name_mark/uu.dsl
zoegas/entries_before_change_name_mark/v.dsl
zoegas/entries_before_change_name_mark/y.dsl
zoegas/entries_before_change_name_mark/yy.dsl
zoegas/inflection/__init__.py
zoegas/inflection/utils.py
zoegas/inflection/__pycache__/__init__.cpython-38.pyc
zoegas/inflection/__pycache__/utils.cpython-38.pyc
zoegas/inflection/old_norse/__init__.py
zoegas/inflection/old_norse/nouns.py
zoegas/inflection/old_norse/phonemic_rules.py
zoegas/inflection/old_norse/pronouns.py
zoegas/inflection/old_norse/verbs.py
zoegas-1.3.1.dist-info/LICENSE
zoegas-1.3.1.dist-info/METADATA
zoegas-1.3.1.dist-info/WHEEL
zoegas-1.3.1.dist-info/top_level.txt
zoegas-1.3.1.dist-info/zip-safe
zoegas-1.3.1.dist-info/RECORD
