Metadata-Version: 2.1
Name: zoegas
Version: 1.3.1
Summary: Old Norse Zoëga's dictionary
Home-page: https://github.com/cltk/old_norse_dictionary_zoega
Author: Clément Besnier
Author-email: clem@clementbesnier.fr
License: License :: OSI Approved :: MIT License
Keywords: nlp,old-norse,philology,dictionary,corpus
Platform: UNKNOWN
Classifier: Programming Language :: Python :: 3
Classifier: Operating System :: OS Independent
Classifier: License :: OSI Approved :: MIT License
Classifier: Topic :: Text Processing
Classifier: Topic :: Text Processing :: Markup :: XML
Requires-Python: >=3.6
Requires-Dist: cltk
Requires-Dist: lxml
